bandwagon/Band.py
bandwagon/BandsPattern.py
bandwagon/BandsPatternsSet.py
bandwagon/__init__.py
bandwagon/ladders.py
bandwagon/plot_records_digestions.py
bandwagon/tools.py
bandwagon/version.py
bandwagon-0.3.4.dist-info/licenses/LICENSE
bandwagon-0.3.4.dist-info/METADATA
bandwagon-0.3.4.dist-info/WHEEL
bandwagon-0.3.4.dist-info/top_level.txt
bandwagon-0.3.4.dist-info/RECORD
