Metadata-Version: 2.4
Name: bandwagon
Version: 0.3.4
Summary: Simulate DNA band patterns for gel migration experiments.
Author: Zulko
License-Expression: MIT
Project-URL: Homepage, https://github.com/Edinburgh-Genome-Foundry/BandWagon
Keywords: gel,agarose,simulation,matplotlib
License-File: LICENSE
Requires-Dist: biopython
Requires-Dist: matplotlib
Requires-Dist: numpy
Requires-Dist: scipy
Requires-Dist: snapgene_reader
Requires-Dist: dna_features_viewer
Provides-Extra: bokeh
Requires-Dist: bokeh; extra == "bokeh"
Requires-Dist: pandas; extra == "bokeh"
Dynamic: license-file
